lucterios/__init__.py
lucterios/contacts/__init__.py
lucterios/contacts/build
lucterios/contacts/editors.py
lucterios/contacts/models.py
lucterios/contacts/test_tools.py
lucterios/contacts/tests.py
lucterios/contacts/tests_contacts.py
lucterios/contacts/tests_possessions.py
lucterios/contacts/tools.py
lucterios/contacts/views.py
lucterios/contacts/views_contacts.py
lucterios/contacts/views_possessions.py
lucterios/contacts/docs/build_en/doctrees/configuration.doctree
lucterios/contacts/docs/build_en/doctrees/environment.pickle
lucterios/contacts/docs/build_en/doctrees/index.doctree
lucterios/contacts/docs/build_en/doctrees/individual.doctree
lucterios/contacts/docs/build_en/doctrees/legal_entity.doctree
lucterios/contacts/docs/build_fr/doctrees/configuration.doctree
lucterios/contacts/docs/build_fr/doctrees/environment.pickle
lucterios/contacts/docs/build_fr/doctrees/index.doctree
lucterios/contacts/docs/build_fr/doctrees/individual.doctree
lucterios/contacts/docs/build_fr/doctrees/legal_entity.doctree
lucterios/contacts/docs/build_fr/doctrees/possession.doctree
lucterios/contacts/docs/en/EditIndividual.png
lucterios/contacts/docs/en/EditLegalEntity.png
lucterios/contacts/docs/en/FindIndividual.png
lucterios/contacts/docs/en/FindLegalEntity.png
lucterios/contacts/docs/en/ListIndividual.png
lucterios/contacts/docs/en/ListLegalEntity.png
lucterios/contacts/docs/en/Makefile
lucterios/contacts/docs/en/ResponsabilityLegalEntity.png
lucterios/contacts/docs/en/ShowIndividual.png
lucterios/contacts/docs/en/ShowLegalEntity.png
lucterios/contacts/docs/en/conf.py
lucterios/contacts/docs/en/configuration.rst
lucterios/contacts/docs/en/index.rst
lucterios/contacts/docs/en/individual.rst
lucterios/contacts/docs/en/legal_entity.rst
lucterios/contacts/docs/fr/Createindividual.png
lucterios/contacts/docs/fr/EditIndividual.png
lucterios/contacts/docs/fr/EditLegalEntity.png
lucterios/contacts/docs/fr/FindIndividual.png
lucterios/contacts/docs/fr/FindLegalEntity.png
lucterios_contacts-2.7.4.25070818.dist-info/licenses/LICENSE
lucterios_contacts-2.7.4.25070818.dist-info/METADATA
lucterios_contacts-2.7.4.25070818.dist-info/WHEEL
lucterios_contacts-2.7.4.25070818.dist-info/top_level.txt
lucterios_contacts-2.7.4.25070818.dist-info/RECORD
